ml4shiptelemetry/RFRegressorModel.py
ml4shiptelemetry/__init__.py
ml4shiptelemetry/__main__.py
ml4shiptelemetry/dataloader.py
ml4shiptelemetry-0.0.2.dist-info/LICENSE
ml4shiptelemetry-0.0.2.dist-info/METADATA
ml4shiptelemetry-0.0.2.dist-info/WHEEL
ml4shiptelemetry-0.0.2.dist-info/top_level.txt
ml4shiptelemetry-0.0.2.dist-info/RECORD
