Metadata-Version: 2.1
Name: ml4shiptelemetry
Version: 0.0.2
Summary: Ship data processing with Machine Learning
Author-email: Antony Zappacosta <antony.zappacosta@dlr.de>, Vytautas Jancauskas <vytautas.jancauskas@dlr.de>
Project-URL: Homepage, https://github.com/DLR-MF-DAS/ml4shiptelemetry
Project-URL: Issues, https://github.com/DLR-MF-DAS/ml4shiptelemetry/issues
Classifier: Programming Language :: Python :: 3
Classifier: License :: OSI Approved :: MIT License
Classifier: Operating System :: OS Independent
Requires-Python: >=3.8
License-File: LICENSE
Requires-Dist: pytest
Requires-Dist: click
Requires-Dist: pdoc
Requires-Dist: numpy
Requires-Dist: pandas
Requires-Dist: matplotlib
Requires-Dist: scikit-learn
